imgtohttps/config.py
imgtohttps/__init__.py
imgtohttps/lib.py
imgtohttps/logic.py
imgtohttps/application.py
imgtohttps/storage.py
imgtohttps-0.5.2.dist-info/DESCRIPTION.rst
imgtohttps-0.5.2.dist-info/METADATA
imgtohttps-0.5.2.dist-info/top_level.txt
imgtohttps-0.5.2.dist-info/metadata.json
imgtohttps-0.5.2.dist-info/RECORD
imgtohttps-0.5.2.dist-info/WHEEL
